{"provides":{"Net::FastCGI::IO":{"version":"0.14","file":"lib/Net/FastCGI/IO.pm"},"Net::FastCGI::Protocol::PP":{"version":"0.14","file":"lib/Net/FastCGI/Protocol/PP.pm"},"Net::FastCGI::Constant":{"version":"0.14","file":"lib/Net/FastCGI/Constant.pm"},"Net::FastCGI":{"version":"0.14","file":"lib/Net/FastCGI.pm"},"Net::FastCGI::Protocol":{"version":"0.14","file":"lib/Net/FastCGI/Protocol.pm"}},"target":"Net::FastCGI","version":"0.14","name":"Net::FastCGI","dist":"Net-FastCGI-0.14","pathname":"C/CH/CHANSEN/Net-FastCGI-0.14.tar.gz"}